nbstripcode/__init__.py
nbstripcode/__main__.py
nbstripcode/main.py
nbstripcode-0.1.1.dist-info/METADATA
nbstripcode-0.1.1.dist-info/WHEEL
nbstripcode-0.1.1.dist-info/entry_points.txt
nbstripcode-0.1.1.dist-info/top_level.txt
nbstripcode-0.1.1.dist-info/RECORD
